asymm_enum/__init__.py
asymm_enum/enum.py
asymm_enum/models.py
asymm_enum/fields/__init__.py
asymm_enum/fields/enumfield.py
asymm_enum/tests/__init__.py
asymm_enum/tests/test_asymm_enum.py
asymm_enum/tests/test_enum_formfield.py
asymm_enum/tests/test_enumfield.py
asymm_enum/tests/test_runner.py
asymm_enum/tests/testapp/__init__.py
asymm_enum/tests/testapp/forms.py
asymm_enum/tests/testapp/models.py
asymm_enum/tests/testapp/urls.py
asymm_enum-0.5.0.post201810181417.dist-info/LICENSE
asymm_enum-0.5.0.post201810181417.dist-info/METADATA
asymm_enum-0.5.0.post201810181417.dist-info/WHEEL
asymm_enum-0.5.0.post201810181417.dist-info/top_level.txt
asymm_enum-0.5.0.post201810181417.dist-info/RECORD
