Metadata-Version: 2.1
Name: asymm-enum
Version: 0.5.0.post201810181417
Summary: Java style enums for Python
Home-page: https://github.com/AsymmetricVentures/asym-enum
Author: Richard Eames
Author-email: reames@asymmetricventures.com
License: GPLv2
Download-URL: https://github.com/AsymmetricVentures/asym-enum/archive/v0.5.0.tar.gz
Platform: UNKNOWN
Classifier: Development Status :: 4 - Beta
Classifier: Framework :: Django
Classifier: Programming Language :: Python
Classifier: Intended Audience :: Developers
Classifier: Natural Language :: English
Classifier: Operating System :: OS Independent
Classifier: Topic :: Software Development :: Libraries
Classifier: Topic :: Utilities
Classifier: License :: OSI Approved :: GNU General Public License v2 (GPLv2)
Classifier: Topic :: Software Development :: Libraries :: Application Frameworks
Requires-Dist: six
